utmp/__init__.py
utmp/__main__.py
utmp/reader.py
utmp-21.10.0.dist-info/LICENSE.txt
utmp-21.10.0.dist-info/METADATA
utmp-21.10.0.dist-info/WHEEL
utmp-21.10.0.dist-info/entry_points.txt
utmp-21.10.0.dist-info/top_level.txt
utmp-21.10.0.dist-info/RECORD
