Metadata-Version: 1.1
Name: utmp
Version: 21.10.0
Summary: utmp/wtmp reader
Home-page: http://srcco.de/
Author: Henning Jacobs
Author-email: henning@jacobs1.de
License: Apache License 2.0
Keywords: utmp wtmp btmp last utmpx wtmpx btmpx
Platform: UNKNOWN
Classifier: Intended Audience :: Developers
Classifier: Development Status :: 4 - Beta
Classifier: Programming Language :: Python
Classifier: Programming Language :: Python :: 3.6
Classifier: Programming Language :: Python :: 3.7
Classifier: Programming Language :: Python :: 3.8
Classifier: Operating System :: POSIX :: Linux
Classifier: License :: OSI Approved :: Apache Software License
